githubInteract/__init__.py
githubInteract/githubInteract.py
githubInteract-0.2.23.dist-info/METADATA
githubInteract-0.2.23.dist-info/WHEEL
githubInteract-0.2.23.dist-info/top_level.txt
githubInteract-0.2.23.dist-info/RECORD
