Metadata-Version: 2.2
Name: githubInteract
Version: 0.2.23
Summary: # GitHub Automation Toolkit Overview
Home-page: https://github.com/brighamturner12/githubInteract.git
Author: Brigham Turner
Author-email: brighamturner@narratebay.com
License: MIT
Project-URL: Documentation, https://github.com/brighamturner12/githubInteract/blob/main/readme.md
Project-URL: Source Code, https://github.com/brighamturner12/githubInteract/blob/main/mygithub2.py
Classifier: Programming Language :: Python :: 3
Classifier: License :: OSI Approved :: MIT License
Classifier: Operating System :: OS Independent
Requires-Python: >=3.6
Requires-Dist: PyGithub
Requires-Dist: gitpython
Dynamic: author
Dynamic: author-email
Dynamic: classifier
Dynamic: description
Dynamic: description-content-type
Dynamic: home-page
Dynamic: license
Dynamic: project-url
Dynamic: requires-dist
Dynamic: requires-python
Dynamic: summary
